live2d/__init__.py
live2d/utils/__init__.py
live2d/utils/canvas.py
live2d/utils/image.py
live2d/utils/lipsync.py
live2d/utils/log.py
live2d/utils/opengl_functions.py
live2d/v2/__init__.py
live2d/v2/lapp_define.py
live2d/v2/lapp_model.py
live2d/v2/matrix_manager.py
live2d/v2/model.py
live2d/v2/model_setting_json.py
live2d/v2/params.py
live2d/v2/platform_manager.py
live2d/v2/core/DEF.py
live2d/v2/core/__init__.py
live2d/v2/core/alive2d_model.py
live2d/v2/core/live2d.py
live2d/v2/core/live2d_gl_wrapper.py
live2d/v2/core/live2d_model_opengl.py
live2d/v2/core/model_context.py
live2d/v2/core/deformer/__init__.py
live2d/v2/core/deformer/deformer.py
live2d/v2/core/deformer/deformer_context.py
live2d/v2/core/deformer/roation_deformer.py
live2d/v2/core/deformer/rotation_context.py
live2d/v2/core/deformer/warp_context.py
live2d/v2/core/deformer/warp_deformer.py
live2d/v2/core/draw/__init__.py
live2d/v2/core/draw/idraw_context.py
live2d/v2/core/draw/idraw_data.py
live2d/v2/core/draw/mesh.py
live2d/v2/core/draw/mesh_context.py
live2d/v2/core/graphics/__init__.py
live2d/v2/core/graphics/clip_context.py
live2d/v2/core/graphics/clip_draw_context.py
live2d/v2/core/graphics/clip_matrix.py
live2d/v2/core/graphics/clip_rectf.py
live2d/v2/core/graphics/clipping_manager_opengl.py
live2d/v2/core/graphics/draw_param.py
live2d/v2/core/graphics/draw_param_opengl.py
live2d/v2/core/graphics/texture_info.py
live2d/v2/core/id/__init__.py
live2d/v2/core/id/id.py
live2d/v2/core/io/__init__.py
live2d/v2/core/io/binary_reader.py
live2d/v2/core/io/iserializable.py
live2d/v2/core/io/live2d_object_factory.py
live2d/v2/core/model/__init__.py
live2d/v2/core/model/avatar.py
live2d/v2/core/model/model_impl.py
live2d/v2/core/model/part.py
live2d/v2/core/model/parts_context.py
live2d/v2/core/motion/__init__.py
live2d/v2/core/motion/amotion.py
live2d/v2/core/motion/live2d_motion.py
live2d/v2/core/motion/motion.py
live2d/v2/core/motion/motion_queue_entry.py
live2d/v2/core/motion/motion_queue_manager.py
live2d_py-0.6.1.1.dist-info/licenses/LICENSE
live2d_py-0.6.1.1.dist-info/METADATA
live2d_py-0.6.1.1.dist-info/WHEEL
live2d_py-0.6.1.1.dist-info/top_level.txt
live2d_py-0.6.1.1.dist-info/RECORD
