Metadata-Version: 2.1
Name: live2d-py
Version: 0.6.1.1
Summary: A non-web Live2D library for Python.
Home-page: https://github.com/Arkueid/live2d-py
Author: Arkueid
Author-email: Arkueid <thetardis@qq.com>
License: LICENSE
Project-URL: Homepage, https://github.com/Arkueid/live2d-py
Project-URL: Documentation, https://Arkueid.github.io/live2d-py-docs/
Project-URL: Repository, https://github.com/Arkueid/live2d-py
Keywords: Live2D,Cubism Live2D,Cubism SDK,Cubism SDK for Python
Requires-Python: >=3.2
License-File: LICENSE
Requires-Dist: pyopengl
Requires-Dist: pillow
Requires-Dist: numpy
